mlkatas/__init__.py
mlkatas/mlkatas.py
mlkatas/plot.py
mlkatas/utils.py
mlkatas-0.0.5.dist-info/LICENSE
mlkatas-0.0.5.dist-info/METADATA
mlkatas-0.0.5.dist-info/WHEEL
mlkatas-0.0.5.dist-info/top_level.txt
mlkatas-0.0.5.dist-info/RECORD
