Metadata-Version: 2.1
Name: mlkatas
Version: 0.0.5
Summary: Utility functions for Machine Learning
Home-page: https://github.com/bpesquet/mlkatas
Author: Baptiste  Pesquet
Author-email: bpesquet@gmail.com
License: MIT
Platform: UNKNOWN
Classifier: Development Status :: 4 - Beta
Classifier: License :: OSI Approved :: MIT License
Classifier: Programming Language :: Python
Classifier: Programming Language :: Python :: 3.6
Classifier: Programming Language :: Python :: 3.7
Classifier: Topic :: Software Development :: Libraries
Classifier: Topic :: Software Development :: Libraries :: Python Modules
Classifier: Intended Audience :: Developers
Requires-Python: >=3.6
Requires-Dist: numpy
Requires-Dist: matplotlib
